philoboard/__init__.py
philoboard-0.0.0.dist-info/METADATA
philoboard-0.0.0.dist-info/WHEEL
philoboard-0.0.0.dist-info/RECORD
